suntransit/__init__.py
suntransit-0.1.0.dist-info/LICENSE
suntransit-0.1.0.dist-info/METADATA
suntransit-0.1.0.dist-info/WHEEL
suntransit-0.1.0.dist-info/top_level.txt
suntransit-0.1.0.dist-info/RECORD
