Metadata-Version: 2.1
Name: suntransit
Version: 0.1.0
Summary: Simple, fast approximation of sunrise, sunset time on Earth
Home-page: UNKNOWN
Author: K. Arthur Endsley
Author-email: arthur.endsley@ntsg.umt.edu
License: UNKNOWN
Platform: UNKNOWN
Classifier: Programming Language :: Python :: 3
Classifier: Development Status :: 5 - Production/Stable
Classifier: Intended Audience :: Science/Research
Classifier: Topic :: Scientific/Engineering
Classifier: Topic :: Scientific/Engineering :: GIS
Requires-Python: >=3.5
License-File: LICENSE
Requires-Dist: numpy (>=1.13.3)
Provides-Extra: docs
Requires-Dist: pdoc3 (>=0.9.2) ; extra == 'docs'
